clingwrap/__init__.py
clingwrap/_version.py
clingwrap/main.py
clingwrap/examples/openstack-kolla-ansible.cwd
clingwrap/examples/shakenfist-ci-failure.cwd
clingwrap/tests/__init__.py
clingwrap-2.1.dist-info/licenses/AUTHORS
clingwrap-2.1.dist-info/licenses/LICENSE
clingwrap-2.1.dist-info/METADATA
clingwrap-2.1.dist-info/WHEEL
clingwrap-2.1.dist-info/entry_points.txt
clingwrap-2.1.dist-info/top_level.txt
clingwrap-2.1.dist-info/RECORD
