Metadata-Version: 2.4
Name: clingwrap
Version: 2.1
Summary: Build bundles of debugging information for system crashes
Project-URL: Homepage, https://shakenfist.com
Project-URL: Bug Tracker, https://github.com/shakenfist/clingwrap/issues
Requires-Python: >=3.7
License-File: LICENSE
License-File: AUTHORS
Requires-Dist: oslo.concurrency
Requires-Dist: click>=7.1.1
Requires-Dist: pyyaml
Requires-Dist: shakenfist-utilities
Provides-Extra: test
Requires-Dist: coverage; extra == "test"
Requires-Dist: testtools; extra == "test"
Requires-Dist: mock; extra == "test"
Requires-Dist: stestr; extra == "test"
Requires-Dist: tox; extra == "test"
Requires-Dist: flake8; extra == "test"
Dynamic: license-file
